{"artists":[{"id":"1","name":"Radiohead","website":"http://radiohead.com/","href":"/api/v1/artists/1"},{"id":"2","name":"Nick Cave \u0026 The Bad Seeds","website":"http://www.nickcave.com/","href":"/api/v1/artists/2"},{"id":"3","name":"John Frusciante","website":"http://johnfrusciante.com/","href":"/api/v1/artists/3"}],"links":{"artists.albums":{"href":"/api/v1/albums?artist_id={artists.id}","type":"albums"},"artists.songs":{"href":"/api/v1/songs?artist_id={artists.id}","type":"songs"}},"meta":{"artists":{"page":1,"page_size":10,"count":3,"include":[],"page_count":1,"previous_page":null,"next_page":null,"previous_href":null,"next_href":null}}}
